[
    {
      "id": 82,
      "levelBoss": 6,
      "status": 4,
      "x": 943,
      "y": 604,
      "paintMiniMap": false,
      "hp": 0,
      "hpFull": 0,
      "level": 0
    },
    {
      "id": 80,
      "levelBoss": 6,
      "status": 4,
      "x": 401,
      "y": 604,
      "paintMiniMap": false,
      "hp": 0,
      "hpFull": 0,
      "level": 0
    },
    {
      "id": 93,
      "levelBoss": 0,
      "status": 4,
      "x": 1132,
      "y": 598,
      "paintMiniMap": false,
      "hp": 0,
      "hpFull": 0,
      "level": 0
    },
    {
      "id": 93,
      "levelBoss": 0,
      "status": 4,
      "x": 1052,
      "y": 598,
      "paintMiniMap": false,
      "hp": 0,
      "hpFull": 0,
      "level": 0
    },
    {
      "id": 93,
      "levelBoss": 0,
      "status": 4,
      "x": 972,
      "y": 598,
      "paintMiniMap": false,
      "hp": 0,
      "hpFull": 0,
      "level": 0
    },
    {
      "id": 93,
      "levelBoss": 0,
      "status": 4,
      "x": 892,
      "y": 598,
      "paintMiniMap": false,
      "hp": 0,
      "hpFull": 0,
      "level": 0
    },
    {
      "id": 93,
      "levelBoss": 0,
      "status": 4,
      "x": 812,
      "y": 598,
      "paintMiniMap": false,
      "hp": 0,
      "hpFull": 0,
      "level": 0
    },
    {
      "id": 93,
      "levelBoss": 0,
      "status": 4,
      "x": 732,
      "y": 598,
      "paintMiniMap": false,
      "hp": 0,
      "hpFull": 0,
      "level": 0
    },
    {
      "id": 93,
      "levelBoss": 0,
      "status": 4,
      "x": 652,
      "y": 598,
      "paintMiniMap": false,
      "hp": 0,
      "hpFull": 0,
      "level": 0
    },
    {
      "id": 93,
      "levelBoss": 0,
      "status": 4,
      "x": 572,
      "y": 598,
      "paintMiniMap": false,
      "hp": 0,
      "hpFull": 0,
      "level": 0
    },
    {
      "id": 93,
      "levelBoss": 0,
      "status": 4,
      "x": 492,
      "y": 598,
      "paintMiniMap": false,
      "hp": 0,
      "hpFull": 0,
      "level": 0
    },
    {
      "id": 93,
      "levelBoss": 0,
      "status": 4,
      "x": 412,
      "y": 598,
      "paintMiniMap": false,
      "hp": 0,
      "hpFull": 0,
      "level": 0
    },
    {
      "id": 93,
      "levelBoss": 0,
      "status": 4,
      "x": 332,
      "y": 598,
      "paintMiniMap": false,
      "hp": 0,
      "hpFull": 0,
      "level": 0
    },
    {
      "id": 93,
      "levelBoss": 0,
      "status": 4,
      "x": 252,
      "y": 598,
      "paintMiniMap": false,
      "hp": 0,
      "hpFull": 0,
      "level": 0
    },
    {
      "id": 93,
      "levelBoss": 0,
      "status": 4,
      "x": 740,
      "y": 508,
      "paintMiniMap": false,
      "hp": 0,
      "hpFull": 0,
      "level": 0
    },
    {
      "id": 93,
      "levelBoss": 0,
      "status": 4,
      "x": 660,
      "y": 508,
      "paintMiniMap": false,
      "hp": 0,
      "hpFull": 0,
      "level": 0
    },
    {
      "id": 93,
      "levelBoss": 0,
      "status": 4,
      "x": 580,
      "y": 508,
      "paintMiniMap": false,
      "hp": 0,
      "hpFull": 0,
      "level": 0
    },
    {
      "id": 85,
      "levelBoss": 6,
      "status": 4,
      "x": 693,
      "y": 507,
      "paintMiniMap": false,
      "hp": 0,
      "hpFull": 0,
      "level": 0
    },
    {
      "id": 93,
      "levelBoss": 0,
      "status": 4,
      "x": 257,
      "y": 472,
      "paintMiniMap": false,
      "hp": 0,
      "hpFull": 0,
      "level": 0
    },
    {
      "id": 93,
      "levelBoss": 0,
      "status": 4,
      "x": 177,
      "y": 472,
      "paintMiniMap": false,
      "hp": 0,
      "hpFull": 0,
      "level": 0
    },
    {
      "id": 93,
      "levelBoss": 0,
      "status": 4,
      "x": 97,
      "y": 472,
      "paintMiniMap": false,
      "hp": 0,
      "hpFull": 0,
      "level": 0
    },
    {
      "id": 93,
      "levelBoss": 0,
      "status": 4,
      "x": 1238,
      "y": 467,
      "paintMiniMap": false,
      "hp": 0,
      "hpFull": 0,
      "level": 0
    },
    {
      "id": 93,
      "levelBoss": 0,
      "status": 4,
      "x": 1158,
      "y": 467,
      "paintMiniMap": false,
      "hp": 0,
      "hpFull": 0,
      "level": 0
    },
    {
      "id": 93,
      "levelBoss": 0,
      "status": 4,
      "x": 1078,
      "y": 467,
      "paintMiniMap": false,
      "hp": 0,
      "hpFull": 0,
      "level": 0
    },
    {
      "id": 93,
      "levelBoss": 0,
      "status": 4,
      "x": 344,
      "y": 362,
      "paintMiniMap": false,
      "hp": 0,
      "hpFull": 0,
      "level": 0
    },
    {
      "id": 93,
      "levelBoss": 0,
      "status": 4,
      "x": 264,
      "y": 362,
      "paintMiniMap": false,
      "hp": 0,
      "hpFull": 0,
      "level": 0
    },
    {
      "id": 93,
      "levelBoss": 0,
      "status": 4,
      "x": 184,
      "y": 362,
      "paintMiniMap": false,
      "hp": 0,
      "hpFull": 0,
      "level": 0
    },
    {
      "id": 83,
      "levelBoss": 6,
      "status": 4,
      "x": 251,
      "y": 357,
      "paintMiniMap": false,
      "hp": 0,
      "hpFull": 0,
      "level": 0
    },
    {
      "id": 93,
      "levelBoss": 0,
      "status": 4,
      "x": 1148,
      "y": 351,
      "paintMiniMap": false,
      "hp": 0,
      "hpFull": 0,
      "level": 0
    },
    {
      "id": 93,
      "levelBoss": 0,
      "status": 4,
      "x": 1068,
      "y": 351,
      "paintMiniMap": false,
      "hp": 0,
      "hpFull": 0,
      "level": 0
    },
    {
      "id": 93,
      "levelBoss": 0,
      "status": 4,
      "x": 988,
      "y": 351,
      "paintMiniMap": false,
      "hp": 0,
      "hpFull": 0,
      "level": 0
    },
    {
      "id": 84,
      "levelBoss": 6,
      "status": 4,
      "x": 1077,
      "y": 348,
      "paintMiniMap": false,
      "hp": 0,
      "hpFull": 0,
      "level": 0
    },
    {
      "id": 93,
      "levelBoss": 0,
      "status": 4,
      "x": 731,
      "y": 273,
      "paintMiniMap": false,
      "hp": 0,
      "hpFull": 0,
      "level": 0
    },
    {
      "id": 93,
      "levelBoss": 0,
      "status": 4,
      "x": 651,
      "y": 273,
      "paintMiniMap": false,
      "hp": 0,
      "hpFull": 0,
      "level": 0
    },
    {
      "id": 81,
      "levelBoss": 6,
      "status": 4,
      "x": 651,
      "y": 273,
      "paintMiniMap": false,
      "hp": 0,
      "hpFull": 0,
      "level": 0
    },
    {
      "id": 93,
      "levelBoss": 0,
      "status": 4,
      "x": 571,
      "y": 273,
      "paintMiniMap": false,
      "hp": 0,
      "hpFull": 0,
      "level": 0
    }
  ]