[{"id":200,"levelBoss":5,"status":2,"x":2294,"y":440,"paintMiniMap":false,"hp":358970,"hpFull":5500000,"level":25},{"id":166,"levelBoss":0,"status":2,"x":1386,"y":481,"paintMiniMap":false,"hp":11000,"hpFull":11000,"level":26},{"id":166,"levelBoss":0,"status":2,"x":1326,"y":481,"paintMiniMap":false,"hp":4920,"hpFull":11000,"level":26},{"id":166,"levelBoss":0,"status":2,"x":1266,"y":481,"paintMiniMap":false,"hp":10302,"hpFull":11000,"level":26},{"id":166,"levelBoss":0,"status":2,"x":1206,"y":481,"paintMiniMap":false,"hp":9631,"hpFull":11000,"level":26},{"id":166,"levelBoss":0,"status":2,"x":1146,"y":481,"paintMiniMap":false,"hp":9949,"hpFull":11000,"level":26},{"id":167,"levelBoss":0,"status":2,"x":1708,"y":470,"paintMiniMap":false,"hp":1991,"hpFull":12000,"level":28},{"id":167,"levelBoss":0,"status":4,"x":1648,"y":470,"paintMiniMap":false,"hp":0,"hpFull":12000,"level":28},{"id":167,"levelBoss":0,"status":2,"x":1588,"y":470,"paintMiniMap":false,"hp":12000,"hpFull":12000,"level":28},{"id":167,"levelBoss":0,"status":4,"x":1528,"y":470,"paintMiniMap":false,"hp":0,"hpFull":12000,"level":28},{"id":167,"levelBoss":0,"status":2,"x":1468,"y":470,"paintMiniMap":false,"hp":12000,"hpFull":12000,"level":28},{"id":166,"levelBoss":0,"status":0,"x":900,"y":439,"paintMiniMap":false,"hp":9496,"hpFull":11000,"level":26},{"id":166,"levelBoss":0,"status":2,"x":840,"y":439,"paintMiniMap":false,"hp":11000,"hpFull":11000,"level":26},{"id":166,"levelBoss":0,"status":2,"x":780,"y":439,"paintMiniMap":false,"hp":11000,"hpFull":11000,"level":26},{"id":166,"levelBoss":0,"status":2,"x":660,"y":439,"paintMiniMap":false,"hp":10309,"hpFull":11000,"level":26},{"id":166,"levelBoss":0,"status":2,"x":600,"y":439,"paintMiniMap":true,"hp":10266,"hpFull":11000,"level":26},{"id":166,"levelBoss":0,"status":2,"x":540,"y":439,"paintMiniMap":false,"hp":11000,"hpFull":11000,"level":26},{"id":166,"levelBoss":0,"status":2,"x":420,"y":439,"paintMiniMap":false,"hp":11000,"hpFull":11000,"level":26},{"id":166,"levelBoss":0,"status":2,"x":360,"y":439,"paintMiniMap":false,"hp":11000,"hpFull":11000,"level":26},{"id":166,"levelBoss":0,"status":2,"x":300,"y":439,"paintMiniMap":false,"hp":11000,"hpFull":11000,"level":26},{"id":167,"levelBoss":0,"status":2,"x":2538,"y":424,"paintMiniMap":false,"hp":12000,"hpFull":12000,"level":28},{"id":167,"levelBoss":0,"status":2,"x":2488,"y":424,"paintMiniMap":false,"hp":12000,"hpFull":12000,"level":28},{"id":167,"levelBoss":0,"status":2,"x":2438,"y":424,"paintMiniMap":false,"hp":12000,"hpFull":12000,"level":28},{"id":167,"levelBoss":0,"status":2,"x":2388,"y":424,"paintMiniMap":false,"hp":12000,"hpFull":12000,"level":28},{"id":167,"levelBoss":0,"status":2,"x":2338,"y":424,"paintMiniMap":false,"hp":12000,"hpFull":12000,"level":28},{"id":167,"levelBoss":0,"status":4,"x":2138,"y":424,"paintMiniMap":false,"hp":0,"hpFull":12000,"level":28},{"id":167,"levelBoss":0,"status":2,"x":2088,"y":424,"paintMiniMap":false,"hp":12000,"hpFull":12000,"level":28},{"id":167,"levelBoss":0,"status":2,"x":2038,"y":424,"paintMiniMap":true,"hp":12000,"hpFull":12000,"level":28},{"id":167,"levelBoss":0,"status":4,"x":1988,"y":424,"paintMiniMap":false,"hp":0,"hpFull":12000,"level":28},{"id":167,"levelBoss":0,"status":4,"x":1938,"y":424,"paintMiniMap":false,"hp":0,"hpFull":12000,"level":28},{"id":167,"levelBoss":0,"status":4,"x":1888,"y":424,"paintMiniMap":false,"hp":0,"hpFull":12000,"level":28}]